.gitattributes
.gitignore
CHANGES.rst
CONTRIBUTING.rst
MANIFEST.in
README.rst
setup.py
plone/__init__.py
plone.formwidget.querystring.egg-info/PKG-INFO
plone.formwidget.querystring.egg-info/SOURCES.txt
plone.formwidget.querystring.egg-info/dependency_links.txt
plone.formwidget.querystring.egg-info/entry_points.txt
plone.formwidget.querystring.egg-info/namespace_packages.txt
plone.formwidget.querystring.egg-info/not-zip-safe
plone.formwidget.querystring.egg-info/requires.txt
plone.formwidget.querystring.egg-info/top_level.txt
plone/formwidget/__init__.py
plone/formwidget/querystring/__init__.py
plone/formwidget/querystring/configure.zcml
plone/formwidget/querystring/converter.py
plone/formwidget/querystring/input.pt
plone/formwidget/querystring/interfaces.py
plone/formwidget/querystring/querywidget.css
plone/formwidget/querystring/querywidget.js
plone/formwidget/querystring/widget.py
plone/formwidget/querystring/profiles/default/cssregistry.xml
plone/formwidget/querystring/profiles/default/jsregistry.xml
plone/formwidget/querystring/profiles/default/metadata.xml