Metadata-Version: 1.1
Name: plone.formwidget.querystring
Version: 1.1.9
Summary: A widget for composing a Query string/search.
Home-page: https://github.com/plone/plone.formwidget.querystring
Author: Plone Foundation
Author-email: plone-developers@lists.sourceforge.net
License: GPL
Keywords: form widget querystring search collection
Platform: UNKNOWN
Classifier: Framework :: Plone
Classifier: Framework :: Plone :: 5.0
Classifier: Framework :: Plone :: 5.1
Classifier: Programming Language :: Python
Classifier: Programming Language :: Python :: 2.7
